mlopus
tests
