Metadata-Version: 2.4
Name: mlOpus
Version: 1.5.2
Summary: MLOps tools for research and development.
Author-email: Lariel Fernandes <lariel.c2.fernandes@gmail.com>
License: Apache-2.0
Project-URL: Repository, https://github.com/lariel-fernandes/mlopus
Classifier: Environment :: Console
Classifier: Operating System :: Unix
Classifier: Development Status :: 3 - Alpha
Classifier: Programming Language :: Python :: 3
Classifier: Intended Audience :: Science/Research
Classifier: Intended Audience :: Information Technology
Classifier: Topic :: Scientific/Engineering :: Artificial Intelligence
Classifier: Topic :: Software Development :: Libraries :: Python Modules
Classifier: License :: OSI Approved :: Apache Software License
Requires-Python: <4,>=3.10
License-File: LICENSE
Requires-Dist: pytz>=2024
Requires-Dist: dacite>=1.5
Requires-Dist: pyyaml>=5
Requires-Dist: urllib3>=1.25
Requires-Dist: pydantic<3,>=2.8
Requires-Dist: packaging>=22
Requires-Dist: rclone-python>=0.1
Requires-Dist: importlib-metadata>=6.8
Requires-Dist: jinja2>=3.1
Provides-Extra: kedro
Requires-Dist: kedro<1,>=0.19; extra == "kedro"
Provides-Extra: search
Requires-Dist: mongomock<5,>=4.1; extra == "search"
Provides-Extra: mlflow
Requires-Dist: mlflow-skinny<3,>=2.9; extra == "mlflow"
Dynamic: license-file
